[
  {
    "has_address": "148 WEST 12 ST, New York, NY 10011",
    "has_city": "New York",
    "has_number": "1089806",
    "co_count": 41,
    "violation_count": 51
  },
  {
    "has_address": "405 LEXINGTON AVENUE, New York, NY",
    "has_city": "New York",
    "has_number": "1036156",
    "co_count": 15,
    "violation_count": 53
  },
  {
    "has_address": "130 WEST 12 STREET, New York, NY",
    "has_city": "New York",
    "has_number": "1088864",
    "co_count": 26,
    "violation_count": 21
  },
  {
    "has_address": "173 5 AVENUE, New York, NY 10010",
    "has_city": "New York",
    "has_number": "1016278",
    "co_count": 0,
    "violation_count": 90
  },
  {
    "has_address": "4 PENN PLAZA, New York, NY",
    "has_city": "New York",
    "has_number": "1082908",
    "co_count": 179,
    "violation_count": 393
  }
]
